MANIFEST.in
README.md
setup.cfg
setup.py
bin/kachery-daemon
bin/kachery-daemon-info
bin/kachery-daemon-start
kachery_daemon/__init__.py
kachery_daemon/_daemon_connection.py
kachery_daemon/_misc.py
kachery_daemon/_preventkeyboardinterrupt.py
kachery_daemon/_shellscript.py
kachery_daemon/_temporarydirectory.py
kachery_daemon/cli.py
kachery_daemon/kachery-daemon-node-1.2.1.tgz
kachery_daemon/start_daemon.py
kachery_daemon/version.py
kachery_daemon.egg-info/PKG-INFO
kachery_daemon.egg-info/SOURCES.txt
kachery_daemon.egg-info/dependency_links.txt
kachery_daemon.egg-info/requires.txt
kachery_daemon.egg-info/top_level.txt