Metadata-Version: 2.1
Name: kachery-daemon
Version: 1.2.1
Summary: Kachery node daemon
Home-page: https://github.com/kacheryhub/kachery-daemon
Author: Jeremy Magland
Author-email: jmagland@flatironinstitute.org
License: UNKNOWN
Project-URL: Bug Tracker, https://github.com/kacheryhub/kachery-daemon/issues
Platform: UNKNOWN
Classifier: Programming Language :: Python :: 3
Classifier: License :: OSI Approved :: Apache Software License
Classifier: Operating System :: OS Independent
